grad_free_optim/NES.py
grad_free_optim/__init__.py
grad_free_optim/pymoo.py
grad_free_optim-0.0.4.dist-info/METADATA
grad_free_optim-0.0.4.dist-info/WHEEL
grad_free_optim-0.0.4.dist-info/top_level.txt
grad_free_optim-0.0.4.dist-info/RECORD
