Metadata-Version: 2.4
Name: grad-free-optim
Version: 0.0.4
Summary: Gradient-free optimization of neural network parameters.
Home-page: https://github.com/NeuroAI-Research/grad-free-optim
Author: Ricky Ding
Author-email: e0134117@u.nus.edu
License: MIT
Keywords: machine-learning,neural-networks,gradient-free,optimization,genetic-algorithm,pytorch
Classifier: Intended Audience :: Science/Research
Classifier: Topic :: Scientific/Engineering :: Artificial Intelligence
Classifier: Programming Language :: Python :: 3
Classifier: Programming Language :: Python :: 3.8
Classifier: License :: OSI Approved :: MIT License
Classifier: Operating System :: OS Independent
Requires-Python: >=3.8
Requires-Dist: numpy
Requires-Dist: torch
Requires-Dist: pymoo
Requires-Dist: trading_models
Dynamic: author
Dynamic: author-email
Dynamic: classifier
Dynamic: description
Dynamic: description-content-type
Dynamic: home-page
Dynamic: keywords
Dynamic: license
Dynamic: requires-dist
Dynamic: requires-python
Dynamic: summary
